flatpack/__init__.py
flatpack/main.py
flatpack/core/__init__.py
flatpack/core/constants.py
flatpack/core/curlang.py
flatpack/managers/__init__.py
flatpack/managers/database.py
flatpack/managers/package.py
flatpack/managers/session.py
flatpack/managers/vector.py
flatpack/resources/__init__.py
flatpack/resources/python_executor.py
flatpack/utils/__init__.py
flatpack/utils/error_handling.py
flatpack/utils/parsers.py
flatpack-3.13.64.dist-info/LICENSE
flatpack-3.13.64.dist-info/METADATA
flatpack-3.13.64.dist-info/WHEEL
flatpack-3.13.64.dist-info/entry_points.txt
flatpack-3.13.64.dist-info/top_level.txt
flatpack-3.13.64.dist-info/RECORD
