Metadata-Version: 2.2
Name: flatpack
Version: 3.13.64
Summary: Ready-to-assemble AI
Home-page: https://codeberg.org/flatpack/Flatpack
Author: Flatpack
Author-email: dev@ƒlatpack.ai
License: Apache-2.0
Classifier: Development Status :: 4 - Beta
Classifier: Intended Audience :: Developers
Classifier: License :: OSI Approved :: Apache Software License
Classifier: Operating System :: POSIX :: Linux
Classifier: Operating System :: MacOS :: MacOS X
Classifier: Operating System :: Microsoft :: Windows
Classifier: Programming Language :: Python :: 3.10
Classifier: Programming Language :: Python :: 3.11
Classifier: Programming Language :: Python :: 3.12
Classifier: Programming Language :: Python :: 3 :: Only
Requires-Python: >=3.10.0, <3.13.0
License-File: LICENSE
Requires-Dist: aiofiles==24.1.0
Requires-Dist: beautifulsoup4==4.13.3
Requires-Dist: croniter==6.0.0
Requires-Dist: cryptography==44.0.1
Requires-Dist: fastapi==0.115.8
Requires-Dist: hnswlib==0.8.0
Requires-Dist: httpx==0.28.1
Requires-Dist: itsdangerous==2.2.0
Requires-Dist: lark==1.2.2
Requires-Dist: ngrok==1.4.0
Requires-Dist: psutil==6.1.1
Requires-Dist: pydantic==2.10.6
Requires-Dist: pypdf==5.3.0
Requires-Dist: python-multipart==0.0.20
Requires-Dist: requests==2.32.3
Requires-Dist: rich==13.9.4
Requires-Dist: sentence-transformers==3.4.1
Requires-Dist: toml==0.10.2
Requires-Dist: uvicorn[standard]==0.34.0
Requires-Dist: zstandard==0.23.0
Dynamic: author
Dynamic: author-email
Dynamic: classifier
Dynamic: description
Dynamic: description-content-type
Dynamic: home-page
Dynamic: license
Dynamic: requires-dist
Dynamic: requires-python
Dynamic: summary
